dis/lab2/a2_b.v
module a2_b(a, b, c, d, f);
	input a, b, c, d;
	output f;

	assign f = (b & ~c) | (c & ~d);
endmodule

dis/lab2/a2_b_tb.v
`timescale 1ns/1ns
`include "a2_b.v"

module a2_b_tb();
	reg a, b, c, d;
	wire f;

	a2_b add2_b(a, b, c, d, f);
	initial begin

		$dumpfile("a2_b_tb.vcd");
		$dumpvars(0, a2_b_tb);
		
		a = 1'b0; b = 1'b0; c = 1'b0; d = 1'b0;
		#20
		
		a = 1'b0; b = 1'b0; c = 1'b0; d = 1'b1;
		#20
		
		a = 1'b0; b = 1'b0; c = 1'b1; d = 1'b0;
		#20
		
		a = 1'b0; b = 1'b0; c = 1'b1; d = 1'b1;
		#20
		
		a = 1'b0; b = 1'b1; c = 1'b0; d = 1'b0;
		#20
		
		a = 1'b0; b = 1'b1; c = 1'b0; d = 1'b1;
		#20
		
		a = 1'b0; b = 1'b1; c = 1'b1; d = 1'b0;
		#20
		
		a = 1'b0; b = 1'b1; c = 1'b1; d = 1'b1;
		#20
		
		a = 1'b1; b = 1'b0; c = 1'b0; d = 1'b0;
		#20
		
		a = 1'b1; b = 1'b0; c = 1'b0; d = 1'b1;
		#20
		
		a = 1'b1; b = 1'b0; c = 1'b1; d = 1'b0;
		#20
		
		a = 1'b1; b = 1'b0; c = 1'b1; d = 1'b1;
		#20
		
		a = 1'b1; b = 1'b1; c = 1'b0; d = 1'b0;
		#20
		
		a = 1'b1; b = 1'b1; c = 1'b0; d = 1'b0;
		#20
		
		a = 1'b1; b = 1'b1; c = 1'b0; d = 1'b0;
		#20
		
		a = 1'b1; b = 1'b1; c = 1'b0; d = 1'b0;
		#20
		
		$display("Test complete");
	
end endmodule

dis/lab2/a2_b_tb.vcd
$date
	Wed Aug  6 17:35:01 2025
$end
$version
	Icarus Verilog
$end
$timescale
	1ns
$end
$scope module a2_b_tb $end
$var wire 1 ! f $end
$var reg 1 " a $end
$var reg 1 # b $end
$var reg 1 $ c $end
$var reg 1 % d $end
$scope module add2_b $end
$var wire 1 " a $end
$var wire 1 # b $end
$var wire 1 $ c $end
$var wire 1 % d $end
$var wire 1 ! f $end
$upscope $end
$upscope $end
$enddefinitions $end
$comment Show the parameter values. $end
$dumpall
$end
#0
$dumpvars
0%
0$
0#
0"
0!
$end
#20
1%
#40
1!
0%
1$
#60
0!
1%
#80
1!
0%
0$
1#
#100
1%
#120
0%
1$
#140
0!
1%
#160
0%
0$
0#
1"
#180
1%
#200
1!
0%
1$
#220
0!
1%
#240
1!
0%
0$
1#
